lightningmcqueen/__init__.py
lightningmcqueen/__main__.py
lightningmcqueen-1.0.2.dist-info/METADATA
lightningmcqueen-1.0.2.dist-info/WHEEL
lightningmcqueen-1.0.2.dist-info/top_level.txt
lightningmcqueen-1.0.2.dist-info/RECORD
