Metadata-Version: 2.1
Name: lightningmcqueen
Version: 1.0.2
Summary: The fastest Python development experience in the galaxy
Home-page: https://replit.com/@notjustinshaw/lightningmcqueen
Author: Justin Shaw
Author-email: realjustinshaw@gmail.com
License: MIT
Platform: UNKNOWN
